lead_lag/__init__.py
lead_lag/contrast.py
lead_lag/lead_lag.py
lead_lag/lead_lag_impl.c
lead_lag/lead_lag_impl.cpython-39-darwin.so
lead_lag/scripts/__init__.py
lead_lag/scripts/display_contrast.py
lead_lag/scripts/main_bachelier.py
lead_lag/scripts/main_bitcoin.py
lead_lag/scripts/read_bachelier_data.py
lead_lag/scripts/read_bitcoin_data.py
lead_lag/scripts/realtime_lead_lag.py
lead_lag/scripts/visualize_contrasts.py
lead_lag-2.1.dist-info/LICENSE
lead_lag-2.1.dist-info/METADATA
lead_lag-2.1.dist-info/WHEEL
lead_lag-2.1.dist-info/top_level.txt
lead_lag-2.1.dist-info/RECORD
